aiida_dataframe/__init__.py
aiida_dataframe/cli.py
aiida_dataframe/data/__init__.py
aiida_dataframe/data/dataframe.py
aiida_dataframe-0.2.0.dist-info/entry_points.txt
aiida_dataframe-0.2.0.dist-info/licenses/LICENSE
aiida_dataframe-0.2.0.dist-info/WHEEL
aiida_dataframe-0.2.0.dist-info/METADATA
aiida_dataframe-0.2.0.dist-info/RECORD
