Metadata-Version: 2.4
Name: aiida-dataframe
Version: 0.2.0
Summary: AiiDA data plugin for pandas DataFrame objects
Keywords: aiida,plugin
Author-email: Henning Janßen <henning.janssen@gmx.net>
Requires-Python: >=3.7
Classifier: Programming Language :: Python
Classifier: Intended Audience :: Science/Research
Classifier: License :: OSI Approved :: MIT License
Classifier: Natural Language :: English
Classifier: Development Status :: 4 - Beta
Classifier: Programming Language :: Python :: 3
Classifier: Programming Language :: Python :: 3.8
Classifier: Programming Language :: Python :: 3.9
Classifier: Programming Language :: Python :: 3.10
Classifier: Programming Language :: Python :: 3.11
Classifier: Framework :: AiiDA
License-File: LICENSE
Requires-Dist: aiida-core>=1.0,<3
Requires-Dist: pandas
Requires-Dist: tables
Requires-Dist: tabulate
Requires-Dist: sphinx ; extra == "docs"
Requires-Dist: sphinxcontrib-contentui ; extra == "docs"
Requires-Dist: sphinxcontrib-details-directive ; extra == "docs"
Requires-Dist: sphinx-autodoc-typehints ; extra == "docs"
Requires-Dist: furo ; extra == "docs"
Requires-Dist: markupsafe<2.1 ; extra == "docs"
Requires-Dist: pre-commit>=2.2 ; extra == "pre-commit"
Requires-Dist: pylint>=2.5.0 ; extra == "pre-commit"
Requires-Dist: pgtest~=1.3.1 ; extra == "testing"
Requires-Dist: wheel~=0.31 ; extra == "testing"
Requires-Dist: coverage[toml] ; extra == "testing"
Requires-Dist: pytest~=6.0 ; extra == "testing"
Requires-Dist: pytest-cov ; extra == "testing"
Requires-Dist: pytest-regressions ; extra == "testing"
Project-URL: Documentation, https://aiida-dataframe.readthedocs.io
Project-URL: Home, https://aiida-dataframe.readthedocs.io
Project-URL: Source, https://github.com/janssenhenning/aiida-dataframe
Provides-Extra: docs
Provides-Extra: pre-commit
Provides-Extra: testing
